stringvibe/__init__.py
stringvibe/core.py
stringvibe-1.0.0.dist-info/METADATA
stringvibe-1.0.0.dist-info/WHEEL
stringvibe-1.0.0.dist-info/top_level.txt
stringvibe-1.0.0.dist-info/RECORD
