Metadata-Version: 2.4
Name: stringvibe
Version: 1.0.0
Summary: Fun to play around with strings such as reverse, etc!
Home-page: https://www.google.com
Author: chrxzrbx
Dynamic: author
Dynamic: home-page
Dynamic: summary
